rattlelib/__init__.py
rattlelib/item.py
rattlelib/render.py
rattlelib/sizeFormatter.py
rattlelib-0.0.1.dist-info/METADATA
rattlelib-0.0.1.dist-info/WHEEL
rattlelib-0.0.1.dist-info/licenses/LICENSE
rattlelib-0.0.1.dist-info/RECORD
